[{"station": "Estacao Jabaquara, Sao Paulo, Brasil", "heuristic-duration": 1591.3948141615165, "heuristic-distance": 35364.32920358926}, {"station": "Estacao Conceicao, Sao Paulo, Brasil", "heuristic-duration": 1534.1523024125293, "heuristic-distance": 34092.2733869451}, {"station": "Estacao Sao Judas, Sao Paulo, Brasil", "heuristic-duration": 1488.0947796900018, "heuristic-distance": 33068.77288200004}, {"station": "Estacao Saude, Sao Paulo, Brasil", "heuristic-duration": 1452.6590937953906, "heuristic-distance": 32281.313195453124}, {"station": "Estacao Praca da arvore, Sao Paulo, Brasil", "heuristic-duration": 1412.9160642339566, "heuristic-distance": 31398.13476075459}, {"station": "Estacao Santa Cruz, Sao Paulo, Brasil", "heuristic-duration": 1354.8512578101443, "heuristic-distance": 30107.805729114316}, {"station": "Estacao Vila Mariana, Sao Paulo, Brasil", "heuristic-duration": 1305.184976620923, "heuristic-distance": 29004.110591576064}, {"station": "Estacao Ana Rosa, Sao Paulo, Brasil", "heuristic-duration": 1268.7631232781491, "heuristic-distance": 28194.736072847754}, {"station": "Estacao Paraiso, Sao Paulo, Brasil", "heuristic-duration": 1236.324235842206, "heuristic-distance": 27473.871907604578}, {"station": "Estacao Vergueiro, Sao Paulo, Brasil", "heuristic-duration": 1205.1471848920812, "heuristic-distance": 26781.04855315736}, {"station": "Estacao Sao Joaquim, Sao Paulo, Brasil", "heuristic-duration": 1170.3551522615908, "heuristic-distance": 26007.892272479792}, {"station": "Estacao Japao-Liberdade, Sao Paulo, Brasil", "heuristic-duration": 1137.0032661353346, "heuristic-distance": 25266.73924745188}, {"station": "Estacao Se, Sao Paulo, Brasil", "heuristic-duration": 1115.5172437996453, "heuristic-distance": 24789.27208443656}, {"station": "Estacao Sao Bento, Sao Paulo, Brasil", "heuristic-duration": 1077.9541999834846, "heuristic-distance": 23954.537777410773}, {"station": "Estacao Luz, Sao Paulo, Brasil", "heuristic-duration": 1044.342034790174, "heuristic-distance": 23207.600773114977}, {"station": "Estacao Armenia, Sao Paulo, Brasil", "heuristic-duration": 986.3049433902326, "heuristic-distance": 21917.88763089406}, {"station": "Estacao Portuguesa-Tiete, Sao Paulo, Brasil", "heuristic-duration": 943.5441099493389, "heuristic-distance": 20967.646887763087}, {"station": "Estacao Carandiru, Sao Paulo, Brasil", "heuristic-duration": 908.2668910196063, "heuristic-distance": 20183.708689324587}, {"station": "Estacao Santana, Sao Paulo, Brasil", "heuristic-duration": 876.616486687468, "heuristic-distance": 19480.366370832624}, {"station": "Estacao Jardim Sao Paulo-Ayrton Senna, Sao Paulo, Brasil", "heuristic-duration": 824.0217538275097, "heuristic-distance": 18311.594529500217}, {"station": "Estacao Parada Inglesa, Sao Paulo, Brasil", "heuristic-duration": 800.2775918036103, "heuristic-distance": 17783.946484524673}, {"station": "Estacao Tucuruvi, Sao Paulo, Brasil", "heuristic-duration": 768.8437260912442, "heuristic-distance": 17085.416135360985}, {"station": "Estacao Vila Prudente, Sao Paulo, Brasil", "heuristic-duration": 1280.8419722831907, "heuristic-distance": 28463.15493962646}, {"station": "Estacao Tamanduatei, Sao Paulo, Brasil", "heuristic-duration": 1326.6591867667555, "heuristic-distance": 29481.31526148345}, {"station": "Estacao Sacoma, Sao Paulo, Brasil", "heuristic-duration": 1375.3370414363178, "heuristic-distance": 30563.045365251503}, {"station": "Estacao Alto do Ipiranga, Sao Paulo, Brasil", "heuristic-duration": 1372.2254631356072, "heuristic-distance": 30493.89918079127}, {"station": "Estacao Santos-Imigrantes, Sao Paulo, Brasil", "heuristic-duration": 1339.8842369673614, "heuristic-distance": 29775.205265941364}, {"station": "Estacao Chacara Klabin, Sao Paulo, Brasil", "heuristic-duration": 1324.3848969928079, "heuristic-distance": 29430.775488729065}, {"station": "Estacao Ana Rosa, Sao Paulo, Brasil", "heuristic-duration": 1268.7631232781491, "heuristic-distance": 28194.736072847754}, {"station": "Estacao Paraiso, Sao Paulo, Brasil", "heuristic-duration": 1236.324235842206, "heuristic-distance": 27473.871907604578}, {"station": "Estacao Brigadeiro, Sao Paulo, Brasil", "heuristic-duration": 1205.8611633154455, "heuristic-distance": 26796.914740343233}, {"station": "Estacao Trianon-Masp, Sao Paulo, Brasil", "heuristic-duration": 1181.5963930332182, "heuristic-distance": 26257.697622960404}, {"station": "Estacao Consolacao, Sao Paulo, Brasil", "heuristic-duration": 1148.5840666288448, "heuristic-distance": 25524.09036952988}, {"station": "Estacao Clinicas, Sao Paulo, Brasil", "heuristic-duration": 1130.783172150087, "heuristic-distance": 25128.5149366686}, {"station": "Estacao S. N. Sra. de Fatima-Sumare, Sao Paulo, Brasil", "heuristic-duration": 1114.4943982304517, "heuristic-distance": 24766.542182898927}, {"station": "Estacao Vila Madalena, Sao Paulo, Brasil", "heuristic-duration": 1093.5768786436947, "heuristic-distance": 24301.70841430433}, {"station": "Estacao Corinthians-Itaquera, Sao Paulo, Brasil", "heuristic-duration": 1076.7522394157463, "heuristic-distance": 23927.82754257214}, {"station": "Estacao Artur Alvim, Sao Paulo, Brasil", "heuristic-duration": 1066.1470292201686, "heuristic-distance": 23692.15620489264}, {"station": "Estacao Patriarca-Vila Re, Sao Paulo, Brasil", "heuristic-duration": 1022.0798270551281, "heuristic-distance": 22712.885045669518}, {"station": "Estacao Guilhermina-Esperanca, Sao Paulo, Brasil", "heuristic-duration": 1013.3332819454284, "heuristic-distance": 22518.517376565076}, {"station": "Estacao Vila Matilde, Sao Paulo, Brasil", "heuristic-duration": 1024.7126264139592, "heuristic-distance": 22771.39169808798}, {"station": "Estacao Penha, Sao Paulo, Brasil", "heuristic-duration": 1022.5870257716158, "heuristic-distance": 22724.156128258128}, {"station": "Estacao Carrao-Assai Atacadista, Sao Paulo, Brasil", "heuristic-duration": 1053.5178319636996, "heuristic-distance": 23411.5073769711}, {"station": "Estacao Tatuape, Sao Paulo, Brasil", "heuristic-duration": 1061.3803505330707, "heuristic-distance": 23586.23001184601}, {"station": "Estacao Belem, Sao Paulo, Brasil", "heuristic-duration": 1080.722556511542, "heuristic-distance": 24016.056811367605}, {"station": "Estacao Bresser-Mooca, Sao Paulo, Brasil", "heuristic-duration": 1096.1469570641964, "heuristic-distance": 24358.821268093252}, {"station": "Estacao Bras, Sao Paulo, Brasil", "heuristic-duration": 1083.2178823392082, "heuristic-distance": 24071.508496426854}, {"station": "Estacao Pedro II, Sao Paulo, Brasil", "heuristic-duration": 1111.17298635424, "heuristic-distance": 24692.733030094223}, {"station": "Estacao Se, Sao Paulo, Brasil", "heuristic-duration": 1115.5172437996453, "heuristic-distance": 24789.27208443656}, {"station": "Estacao Anhangabau, Sao Paulo, Brasil", "heuristic-duration": 1097.915944726997, "heuristic-distance": 24398.132105044373}, {"station": "Estacao Republica, Sao Paulo, Brasil", "heuristic-duration": 1079.1935578049438, "heuristic-distance": 23982.07906233209}, {"station": "Estacao Santa Cecilia, Sao Paulo, Brasil", "heuristic-duration": 1054.9615496693543, "heuristic-distance": 23443.58999265232}, {"station": "Estacao Marechal Deodoro, Sao Paulo, Brasil", "heuristic-duration": 1030.5067157571812, "heuristic-distance": 22900.14923904847}, {"station": "Estacao Palmeiras-Barra Funda, Sao Paulo, Brasil", "heuristic-duration": 983.2117670995015, "heuristic-distance": 21849.150379988925}, {"station": "Estacao Vila Sonia Profa. Elisabeth Tenreiro, Sao Paulo, Brasil", "heuristic-duration": 1321.1301082760776, "heuristic-distance": 29358.4468505795}, {"station": "Estacao Sao Paulo-Morumbi, Sao Paulo, Brasil", "heuristic-duration": 1291.2272899104546, "heuristic-distance": 28693.939775787883}, {"station": "Estacao Butanta, Sao Paulo, Brasil", "heuristic-duration": 1220.1518690019807, "heuristic-distance": 27114.485977821794}, {"station": "Estacao Pinheiros, Sao Paulo, Brasil", "heuristic-duration": 1193.647078592637, "heuristic-distance": 26525.490635391932}, {"station": "Estacao Faria Lima, Sao Paulo, Brasil", "heuristic-duration": 1197.9627036977156, "heuristic-distance": 26621.393415504794}, {"station": "Estacao Fradique Coutinho, Sao Paulo, Brasil", "heuristic-duration": 1191.9662963613366, "heuristic-distance": 26488.13991914081}, {"station": "Estacao Oscar Freire, Sao Paulo, Brasil", "heuristic-duration": 1164.9526563489683, "heuristic-distance": 25887.83680775485}, {"station": "Estacao Paulista Pernambucanas, Sao Paulo, Brasil", "heuristic-duration": 1136.1087376819144, "heuristic-distance": 25246.860837375876}, {"station": "Estacao Higienopolis-Mackenzie, Sao Paulo, Brasil", "heuristic-duration": 1106.5765699432106, "heuristic-distance": 24590.590443182457}, {"station": "Estacao Republica, Sao Paulo, Brasil", "heuristic-duration": 1079.1935578049438, "heuristic-distance": 23982.07906233209}, {"station": "Estacao Luz, Sao Paulo, Brasil", "heuristic-duration": 1044.342034790174, "heuristic-distance": 23207.600773114977}, {"station": "Estacao Capao Redondo, Sao Paulo, Brasil", "heuristic-duration": 1658.5002898464058, "heuristic-distance": 36855.561996586795}, {"station": "Estacao Campo Limpo, Sao Paulo, Brasil", "heuristic-duration": 1610.1495183367504, "heuristic-distance": 35781.10040748334}, {"station": "Estacao Vila das Belezas, Sao Paulo, Brasil", "heuristic-duration": 1564.23463296284, "heuristic-distance": 34760.769621396445}, {"station": "Estacao Giovanni Gronchi, Sao Paulo, Brasil", "heuristic-duration": 1583.5967690914158, "heuristic-distance": 35191.03931314257}, {"station": "Estacao Santo Amaro, Sao Paulo, Brasil", "heuristic-duration": 1638.4847959260412, "heuristic-distance": 36410.77324280091}, {"station": "Estacao Largo Treze, Sao Paulo, Brasil", "heuristic-duration": 1630.7141125226108, "heuristic-distance": 36238.09138939135}, {"station": "Estacao Adolfo Pinheiro, Sao Paulo, Brasil", "heuristic-duration": 1611.6941546092312, "heuristic-distance": 35815.42565798291}, {"station": "Estacao Alto da Boa Vista, Sao Paulo, Brasil", "heuristic-duration": 1569.9424053925177, "heuristic-distance": 34887.60900872262}, {"station": "Estacao Borba Gato, Sao Paulo, Brasil", "heuristic-duration": 1528.787076726749, "heuristic-distance": 33973.04614948332}, {"station": "Estacao Brooklin, Sao Paulo, Brasil", "heuristic-duration": 1496.7344055363758, "heuristic-distance": 33260.76456747501}, {"station": "Estacao Campo Belo, Sao Paulo, Brasil", "heuristic-duration": 1454.4915922332343, "heuristic-distance": 32322.03538296076}, {"station": "Estacao Eucaliptos, Sao Paulo, Brasil", "heuristic-duration": 1410.8712500523882, "heuristic-distance": 31352.694445608624}, {"station": "Estacao Moema, Sao Paulo, Brasil", "heuristic-duration": 1378.0031539258564, "heuristic-distance": 30622.29230946348}, {"station": "Estacao AACD-Servidor, Sao Paulo, Brasil", "heuristic-duration": 1348.755351850096, "heuristic-distance": 29972.341152224355}, {"station": "Estacao Hospital Sao Paulo, Sao Paulo, Brasil", "heuristic-duration": 1352.3515767240242, "heuristic-distance": 30052.257260533872}, {"station": "Estacao Santa Cruz, Sao Paulo, Brasil", "heuristic-duration": 1354.8512578101443, "heuristic-distance": 30107.805729114316}, {"station": "Estacao Chacara Klabin, Sao Paulo, Brasil", "heuristic-duration": 1324.3848969928079, "heuristic-distance": 29430.775488729065}, {"station": "Estacao Vila Prudente, Sao Paulo, Brasil", "heuristic-duration": 1280.8419722831907, "heuristic-distance": 28463.15493962646}, {"station": "Estacao Oratorio, Sao Paulo, Brasil", "heuristic-duration": 1269.8460788835353, "heuristic-distance": 28218.801752967447}, {"station": "Estacao Sao Lucas, Sao Paulo, Brasil", "heuristic-duration": 1303.7716453698201, "heuristic-distance": 28972.703230440442}, {"station": "Estacao Camilo Haddad, Sao Paulo, Brasil", "heuristic-duration": 1336.574288476261, "heuristic-distance": 29701.650855028023}, {"station": "Estacao Vila Tolstoi, Sao Paulo, Brasil", "heuristic-duration": 1361.89498466858, "heuristic-distance": 30264.33299263511}, {"station": "Estacao Vila Uniao, Sao Paulo, Brasil", "heuristic-duration": 1371.577555068677, "heuristic-distance": 30479.501223748375}, {"station": "Estacao Jd. Planalto, Sao Paulo, Brasil", "heuristic-duration": 1389.533523144167, "heuristic-distance": 30878.522736537045}, {"station": "Estacao Sapopemba, Sao Paulo, Brasil", "heuristic-duration": 1321.5759884281738, "heuristic-distance": 29368.355298403865}, {"station": "Estacao Fazenda da Juta, Sao Paulo, Brasil", "heuristic-duration": 1417.0613481748167, "heuristic-distance": 31490.252181662592}, {"station": "Estacao Sao Mateus, Sao Paulo, Brasil", "heuristic-duration": 1415.2967449531614, "heuristic-distance": 31451.038776736914}, {"station": "Estacao Luz, Sao Paulo, Brasil", "heuristic-duration": 1044.342034790174, "heuristic-distance": 23207.600773114977}, {"station": "Estacao Palmeiras-Barra Funda, Sao Paulo, Brasil", "heuristic-duration": 983.2117670995015, "heuristic-distance": 21849.150379988925}, {"station": "Estacao agua Branca, Sao Paulo, Brasil", "heuristic-duration": 967.2198248658012, "heuristic-distance": 21493.773885906696}, {"station": "Estacao Lapa, Sao Paulo, Brasil", "heuristic-duration": 963.1879834044088, "heuristic-distance": 21404.17740898686}, {"station": "Estacao Piqueri, Sao Paulo, Brasil", "heuristic-duration": 880.2379109973966, "heuristic-distance": 19560.842466608814}, {"station": "Estacao Pirituba, Sao Paulo, Brasil", "heuristic-duration": 799.9934312513884, "heuristic-distance": 17777.63180558641}, {"station": "Estacao Vila Clarice, Sao Paulo, Brasil", "heuristic-duration": 712.2788679680375, "heuristic-distance": 15828.419288178613}, {"station": "Estacao Jaragua, Sao Paulo, Brasil", "heuristic-duration": 630.8521808187425, "heuristic-distance": 14018.937351527611}, {"station": "Estacao Vila Aurora, Sao Paulo, Brasil", "heuristic-duration": 554.0182587726609, "heuristic-distance": 12311.516861614688}, {"station": "Estacao Perus, Sao Paulo, Brasil", "heuristic-duration": 386.47076873787057, "heuristic-distance": 8588.239305286013}, {"station": "Estacao Caieiras, Melhoramentos, Caieiras, SP, 07700-000", "heuristic-duration": 194.66978767751743, "heuristic-distance": 4325.995281722609}, {"station": "Estacao Franco da Rocha, Sao Paulo, Brasil", "heuristic-duration": 0.0, "heuristic-distance": 0.0}, {"station": "Estacao Baltazar Fidelis, Sao Paulo, Brasil", "heuristic-duration": 88.4754832245316, "heuristic-distance": 1966.1218494340358}, {"station": "Estacao Francisco Morato, Sao Paulo, Brasil", "heuristic-duration": 228.48632726819366, "heuristic-distance": 5077.473939293192}, {"station": "Estacao Botujuru, Sao Paulo, Brasil", "heuristic-duration": 462.2809692098715, "heuristic-distance": 10272.910426886034}, {"station": "Estacao Campo Limpo Paulista, Sao Paulo, Brasil", "heuristic-duration": 614.7840732788029, "heuristic-distance": 13661.868295084509}, {"station": "Estacao Varzea Paulista, Sao Paulo, Brasil", "heuristic-duration": 613.0995017986658, "heuristic-distance": 13624.433373303684}, {"station": "Estacao Jundiai, Sao Paulo, Brasil", "heuristic-duration": 697.9411809881005, "heuristic-distance": 15509.804021957789}]