[{"station": "Estacao Jabaquara, Sao Paulo, Brasil", "heuristic-duration": 718.6058782032479, "heuristic-distance": 15969.019515627731}, {"station": "Estacao Conceicao, Sao Paulo, Brasil", "heuristic-duration": 665.2462208710847, "heuristic-distance": 14783.249352690771}, {"station": "Estacao Sao Judas, Sao Paulo, Brasil", "heuristic-duration": 615.0942653015195, "heuristic-distance": 13668.761451144877}, {"station": "Estacao Saude, Sao Paulo, Brasil", "heuristic-duration": 579.6195998872903, "heuristic-distance": 12880.435553050893}, {"station": "Estacao Praca da arvore, Sao Paulo, Brasil", "heuristic-duration": 539.8005832478098, "heuristic-distance": 11995.568516617992}, {"station": "Estacao Santa Cruz, Sao Paulo, Brasil", "heuristic-duration": 481.60832134912914, "heuristic-distance": 10702.407141091757}, {"station": "Estacao Vila Mariana, Sao Paulo, Brasil", "heuristic-duration": 431.8204063528442, "heuristic-distance": 9596.009030063204}, {"station": "Estacao Ana Rosa, Sao Paulo, Brasil", "heuristic-duration": 395.24661712181813, "heuristic-distance": 8783.258158262626}, {"station": "Estacao Paraiso, Sao Paulo, Brasil", "heuristic-duration": 362.6940234087108, "heuristic-distance": 8059.8671868602405}, {"station": "Estacao Vergueiro, Sao Paulo, Brasil", "heuristic-duration": 331.41816108500615, "heuristic-distance": 7364.8480241112475}, {"station": "Estacao Sao Joaquim, Sao Paulo, Brasil", "heuristic-duration": 296.5100412726896, "heuristic-distance": 6589.11202828199}, {"station": "Estacao Japao-Liberdade, Sao Paulo, Brasil", "heuristic-duration": 263.02670862337567, "heuristic-distance": 5845.0379694083485}, {"station": "Estacao Se, Sao Paulo, Brasil", "heuristic-duration": 235.53338936583503, "heuristic-distance": 5234.075319240778}, {"station": "Estacao Sao Bento, Sao Paulo, Brasil", "heuristic-duration": 203.71859875716638, "heuristic-distance": 4527.079972381475}, {"station": "Estacao Luz, Sao Paulo, Brasil", "heuristic-duration": 170.10306567344213, "heuristic-distance": 3780.068126076492}, {"station": "Estacao Armenia, Sao Paulo, Brasil", "heuristic-duration": 114.43227904473109, "heuristic-distance": 2542.9395343273577}, {"station": "Estacao Portuguesa-Tiete, Sao Paulo, Brasil", "heuristic-duration": 68.35011756941651, "heuristic-distance": 1518.8915015425894}, {"station": "Estacao Carandiru, Sao Paulo, Brasil", "heuristic-duration": 32.83481716725919, "heuristic-distance": 729.6626037168709}, {"station": "Estacao Santana, Sao Paulo, Brasil", "heuristic-duration": 0.0, "heuristic-distance": 0.0}, {"station": "Estacao Jardim Sao Paulo-Ayrton Senna, Sao Paulo, Brasil", "heuristic-duration": 49.44756578806417, "heuristic-distance": 1098.8347952903148}, {"station": "Estacao Parada Inglesa, Sao Paulo, Brasil", "heuristic-duration": 77.02831642346773, "heuristic-distance": 1711.7403649659498}, {"station": "Estacao Tucuruvi, Sao Paulo, Brasil", "heuristic-duration": 109.31411794444769, "heuristic-distance": 2429.2026209877267}, {"station": "Estacao Vila Prudente, Sao Paulo, Brasil", "heuristic-duration": 407.9247901371884, "heuristic-distance": 9064.995336381962}, {"station": "Estacao Tamanduatei, Sao Paulo, Brasil", "heuristic-duration": 453.9832984255611, "heuristic-distance": 10088.517742790247}, {"station": "Estacao Sacoma, Sao Paulo, Brasil", "heuristic-duration": 502.7365793168692, "heuristic-distance": 11171.923984819317}, {"station": "Estacao Alto do Ipiranga, Sao Paulo, Brasil", "heuristic-duration": 499.445542428843, "heuristic-distance": 11098.789831752067}, {"station": "Estacao Santos-Imigrantes, Sao Paulo, Brasil", "heuristic-duration": 466.81688504909596, "heuristic-distance": 10373.708556646576}, {"station": "Estacao Chacara Klabin, Sao Paulo, Brasil", "heuristic-duration": 451.1363679551318, "heuristic-distance": 10025.25262122515}, {"station": "Estacao Ana Rosa, Sao Paulo, Brasil", "heuristic-duration": 395.24661712181813, "heuristic-distance": 8783.258158262626}, {"station": "Estacao Paraiso, Sao Paulo, Brasil", "heuristic-duration": 362.6940234087108, "heuristic-distance": 8059.8671868602405}, {"station": "Estacao Brigadeiro, Sao Paulo, Brasil", "heuristic-duration": 332.1103027179781, "heuristic-distance": 7380.228949288403}, {"station": "Estacao Trianon-Masp, Sao Paulo, Brasil", "heuristic-duration": 307.7744105823623, "heuristic-distance": 6839.431346274718}, {"station": "Estacao Consolacao, Sao Paulo, Brasil", "heuristic-duration": 277.08022861479486, "heuristic-distance": 6157.338413662107}, {"station": "Estacao Clinicas, Sao Paulo, Brasil", "heuristic-duration": 256.9310682287695, "heuristic-distance": 5709.579293972656}, {"station": "Estacao S. N. Sra. de Fatima-Sumare, Sao Paulo, Brasil", "heuristic-duration": 240.6859806741071, "heuristic-distance": 5348.577348313492}, {"station": "Estacao Vila Madalena, Sao Paulo, Brasil", "heuristic-duration": 219.91403992144296, "heuristic-distance": 4886.9786649209545}, {"station": "Estacao Corinthians-Itaquera, Sao Paulo, Brasil", "heuristic-duration": 201.05845728271007, "heuristic-distance": 4467.9657173935575}, {"station": "Estacao Artur Alvim, Sao Paulo, Brasil", "heuristic-duration": 190.3850496993572, "heuristic-distance": 4230.778882207938}, {"station": "Estacao Patriarca-Vila Re, Sao Paulo, Brasil", "heuristic-duration": 146.09983210688, "heuristic-distance": 3246.662935708445}, {"station": "Estacao Guilhermina-Esperanca, Sao Paulo, Brasil", "heuristic-duration": 137.35415501157547, "heuristic-distance": 3052.314555812788}, {"station": "Estacao Vila Matilde, Sao Paulo, Brasil", "heuristic-duration": 148.82460642426548, "heuristic-distance": 3307.213476094789}, {"station": "Estacao Penha, Sao Paulo, Brasil", "heuristic-duration": 146.7563679291289, "heuristic-distance": 3261.252620647309}, {"station": "Estacao Carrao-Assai Atacadista, Sao Paulo, Brasil", "heuristic-duration": 178.35969873629105, "heuristic-distance": 3963.548860806468}, {"station": "Estacao Tatuape, Sao Paulo, Brasil", "heuristic-duration": 186.41282235223065, "heuristic-distance": 4142.507163382904}, {"station": "Estacao Belem, Sao Paulo, Brasil", "heuristic-duration": 206.0704178044368, "heuristic-distance": 4579.342617876374}, {"station": "Estacao Bresser-Mooca, Sao Paulo, Brasil", "heuristic-duration": 221.7666732345601, "heuristic-distance": 4928.1482941013355}, {"station": "Estacao Bras, Sao Paulo, Brasil", "heuristic-duration": 208.8380977886592, "heuristic-distance": 4640.84661752576}, {"station": "Estacao Pedro II, Sao Paulo, Brasil", "heuristic-duration": 237.031337599563, "heuristic-distance": 5267.363057768067}, {"station": "Estacao Se, Sao Paulo, Brasil", "heuristic-duration": 235.53338936583503, "heuristic-distance": 5234.075319240778}, {"station": "Estacao Anhangabau, Sao Paulo, Brasil", "heuristic-duration": 230.28588490983685, "heuristic-distance": 5117.464109107486}, {"station": "Estacao Republica, Sao Paulo, Brasil", "heuristic-duration": 205.05816370994438, "heuristic-distance": 4556.848082443208}, {"station": "Estacao Santa Cecilia, Sao Paulo, Brasil", "heuristic-duration": 180.8106970188551, "heuristic-distance": 4018.015489307891}, {"station": "Estacao Marechal Deodoro, Sao Paulo, Brasil", "heuristic-duration": 156.420786282407, "heuristic-distance": 3476.0174729423775}, {"station": "Estacao Palmeiras-Barra Funda, Sao Paulo, Brasil", "heuristic-duration": 109.46482274128607, "heuristic-distance": 2432.551616473024}, {"station": "Estacao Vila Sonia Profa. Elisabeth Tenreiro, Sao Paulo, Brasil", "heuristic-duration": 446.6770855761467, "heuristic-distance": 9926.157457247704}, {"station": "Estacao Sao Paulo-Morumbi, Sao Paulo, Brasil", "heuristic-duration": 416.9572537162867, "heuristic-distance": 9265.716749250814}, {"station": "Estacao Butanta, Sao Paulo, Brasil", "heuristic-duration": 346.167518275043, "heuristic-distance": 7692.6115172231775}, {"station": "Estacao Pinheiros, Sao Paulo, Brasil", "heuristic-duration": 319.74353274891257, "heuristic-distance": 7105.411838864723}, {"station": "Estacao Faria Lima, Sao Paulo, Brasil", "heuristic-duration": 324.07314611029665, "heuristic-distance": 7201.625469117703}, {"station": "Estacao Fradique Coutinho, Sao Paulo, Brasil", "heuristic-duration": 318.1041530567956, "heuristic-distance": 7068.981179039903}, {"station": "Estacao Oscar Freire, Sao Paulo, Brasil", "heuristic-duration": 290.5753596795955, "heuristic-distance": 6457.230215102121}, {"station": "Estacao Paulista Pernambucanas, Sao Paulo, Brasil", "heuristic-duration": 262.9557232240294, "heuristic-distance": 5843.460516089542}, {"station": "Estacao Higienopolis-Mackenzie, Sao Paulo, Brasil", "heuristic-duration": 232.58866252878414, "heuristic-distance": 5168.636945084092}, {"station": "Estacao Republica, Sao Paulo, Brasil", "heuristic-duration": 205.05816370994438, "heuristic-distance": 4556.848082443208}, {"station": "Estacao Luz, Sao Paulo, Brasil", "heuristic-duration": 170.10306567344213, "heuristic-distance": 3780.068126076492}, {"station": "Estacao Capao Redondo, Sao Paulo, Brasil", "heuristic-duration": 783.0779878747276, "heuristic-distance": 17401.73306388284}, {"station": "Estacao Campo Limpo, Sao Paulo, Brasil", "heuristic-duration": 734.9015965533408, "heuristic-distance": 16331.14659007424}, {"station": "Estacao Vila das Belezas, Sao Paulo, Brasil", "heuristic-duration": 689.2188637717732, "heuristic-distance": 15315.974750483847}, {"station": "Estacao Giovanni Gronchi, Sao Paulo, Brasil", "heuristic-duration": 708.7348618315331, "heuristic-distance": 15749.663596256292}, {"station": "Estacao Santo Amaro, Sao Paulo, Brasil", "heuristic-duration": 763.8569677031741, "heuristic-distance": 16974.59928229276}, {"station": "Estacao Largo Treze, Sao Paulo, Brasil", "heuristic-duration": 756.2309829222679, "heuristic-distance": 16805.13295382817}, {"station": "Estacao Adolfo Pinheiro, Sao Paulo, Brasil", "heuristic-duration": 737.3542537122808, "heuristic-distance": 16385.65008249513}, {"station": "Estacao Alto da Boa Vista, Sao Paulo, Brasil", "heuristic-duration": 695.7205326829144, "heuristic-distance": 15460.456281842542}, {"station": "Estacao Borba Gato, Sao Paulo, Brasil", "heuristic-duration": 654.7050176591665, "heuristic-distance": 14549.000392425922}, {"station": "Estacao Brooklin, Sao Paulo, Brasil", "heuristic-duration": 622.7484003149106, "heuristic-distance": 13838.853340331347}, {"station": "Estacao Campo Belo, Sao Paulo, Brasil", "heuristic-duration": 580.6078637015444, "heuristic-distance": 12902.396971145432}, {"station": "Estacao Eucaliptos, Sao Paulo, Brasil", "heuristic-duration": 538.6409582675793, "heuristic-distance": 11969.799072612874}, {"station": "Estacao Moema, Sao Paulo, Brasil", "heuristic-duration": 504.41809542357186, "heuristic-distance": 11209.291009412707}, {"station": "Estacao AACD-Servidor, Sao Paulo, Brasil", "heuristic-duration": 475.265656097589, "heuristic-distance": 10561.459024390868}, {"station": "Estacao Hospital Sao Paulo, Sao Paulo, Brasil", "heuristic-duration": 478.97067979584455, "heuristic-distance": 10643.7928843521}, {"station": "Estacao Santa Cruz, Sao Paulo, Brasil", "heuristic-duration": 481.60832134912914, "heuristic-distance": 10702.407141091757}, {"station": "Estacao Chacara Klabin, Sao Paulo, Brasil", "heuristic-duration": 451.1363679551318, "heuristic-distance": 10025.25262122515}, {"station": "Estacao Vila Prudente, Sao Paulo, Brasil", "heuristic-duration": 407.9247901371884, "heuristic-distance": 9064.995336381962}, {"station": "Estacao Oratorio, Sao Paulo, Brasil", "heuristic-duration": 397.06579501625964, "heuristic-distance": 8823.68433369466}, {"station": "Estacao Sao Lucas, Sao Paulo, Brasil", "heuristic-duration": 431.5715339449565, "heuristic-distance": 9590.478532110144}, {"station": "Estacao Camilo Haddad, Sao Paulo, Brasil", "heuristic-duration": 464.8752637719077, "heuristic-distance": 10330.561417153505}, {"station": "Estacao Vila Tolstoi, Sao Paulo, Brasil", "heuristic-duration": 490.7098913226339, "heuristic-distance": 10904.664251614086}, {"station": "Estacao Vila Uniao, Sao Paulo, Brasil", "heuristic-duration": 500.78283698511734, "heuristic-distance": 11128.507488558163}, {"station": "Estacao Jd. Planalto, Sao Paulo, Brasil", "heuristic-duration": 518.9963358478778, "heuristic-distance": 11533.25190773062}, {"station": "Estacao Sapopemba, Sao Paulo, Brasil", "heuristic-duration": 449.7688782401678, "heuristic-distance": 9994.863960892619}, {"station": "Estacao Fazenda da Juta, Sao Paulo, Brasil", "heuristic-duration": 547.5156294226044, "heuristic-distance": 12167.013987168988}, {"station": "Estacao Sao Mateus, Sao Paulo, Brasil", "heuristic-duration": 546.0573707594106, "heuristic-distance": 12134.608239098014}, {"station": "Estacao Luz, Sao Paulo, Brasil", "heuristic-duration": 170.10306567344213, "heuristic-distance": 3780.068126076492}, {"station": "Estacao Palmeiras-Barra Funda, Sao Paulo, Brasil", "heuristic-duration": 109.46482274128607, "heuristic-distance": 2432.551616473024}, {"station": "Estacao agua Branca, Sao Paulo, Brasil", "heuristic-duration": 94.51011326308398, "heuristic-distance": 2100.224739179644}, {"station": "Estacao Lapa, Sao Paulo, Brasil", "heuristic-duration": 91.15410286775936, "heuristic-distance": 2025.6467303946522}, {"station": "Estacao Piqueri, Sao Paulo, Brasil", "heuristic-duration": 27.13133386121242, "heuristic-distance": 602.9185302491649}, {"station": "Estacao Pirituba, Sao Paulo, Brasil", "heuristic-duration": 80.29656991071312, "heuristic-distance": 1784.3682202380692}, {"station": "Estacao Vila Clarice, Sao Paulo, Brasil", "heuristic-duration": 167.64887971730084, "heuristic-distance": 3725.5306603844638}, {"station": "Estacao Jaragua, Sao Paulo, Brasil", "heuristic-duration": 247.35507511364452, "heuristic-distance": 5496.779446969877}, {"station": "Estacao Vila Aurora, Sao Paulo, Brasil", "heuristic-duration": 324.5169804680692, "heuristic-distance": 7211.488454845982}, {"station": "Estacao Perus, Sao Paulo, Brasil", "heuristic-duration": 492.2669879327837, "heuristic-distance": 10939.266398506305}, {"station": "Estacao Caieiras, Melhoramentos, Caieiras, SP, 07700-000", "heuristic-duration": 684.699284069501, "heuristic-distance": 15215.539645988913}, {"station": "Estacao Franco da Rocha, Sao Paulo, Brasil", "heuristic-duration": 876.0503394502699, "heuristic-distance": 19467.78532111711}, {"station": "Estacao Baltazar Fidelis, Sao Paulo, Brasil", "heuristic-duration": 964.4550907743145, "heuristic-distance": 21432.335350540317}, {"station": "Estacao Francisco Morato, Sao Paulo, Brasil", "heuristic-duration": 1103.9477925676465, "heuristic-distance": 24532.173168169924}, {"station": "Estacao Botujuru, Sao Paulo, Brasil", "heuristic-duration": 1335.9550600524362, "heuristic-distance": 29687.89022338747}, {"station": "Estacao Campo Limpo Paulista, Sao Paulo, Brasil", "heuristic-duration": 1487.0461889533176, "heuristic-distance": 33045.47086562927}, {"station": "Estacao Varzea Paulista, Sao Paulo, Brasil", "heuristic-duration": 1476.0424079360055, "heuristic-distance": 32800.9423985779}, {"station": "Estacao Jundiai, Sao Paulo, Brasil", "heuristic-duration": 1548.810664437581, "heuristic-distance": 34418.01476527957}]